tests/__init__.py
tests/test_worldmapper.py
worldmapper/__init__.py
worldmapper/data.py
worldmapper/world.json
worldmapper-0.1.3.dist-info/licenses/LICENSE
worldmapper-0.1.3.dist-info/METADATA
worldmapper-0.1.3.dist-info/WHEEL
worldmapper-0.1.3.dist-info/top_level.txt
worldmapper-0.1.3.dist-info/RECORD
