Metadata-Version: 2.4
Name: worldmapper
Version: 0.1.3
Summary: A Python package for accessing world country, state, and city information
Home-page: https://github.com/fatih-koc/worldmapper
Author: Fatih Koçkesen
Author-email: Fatih Koçkesen <fatihinemaili@gmail.com>
License: MIT
Project-URL: Homepage, https://github.com/fatih-koc/worldmapper
Project-URL: Repository, https://github.com/fatih-koc/worldmapper
Classifier: Development Status :: 3 - Alpha
Classifier: Intended Audience :: Developers
Classifier: License :: OSI Approved :: MIT License
Classifier: Operating System :: OS Independent
Classifier: Programming Language :: Python :: 3
Requires-Python: >=3.7
License-File: LICENSE
Dynamic: author
Dynamic: home-page
Dynamic: license-file
Dynamic: requires-python
